scirpy/__init__.py
scirpy/datasets/__init__.py
scirpy/datasets/_processing_scripts/.gitignore
scirpy/datasets/_processing_scripts/3k_barcodes.csv
scirpy/datasets/_processing_scripts/README.md
scirpy/datasets/_processing_scripts/jupytext.toml
scirpy/datasets/_processing_scripts/maynard2020.py
scirpy/datasets/_processing_scripts/wu2020.py
scirpy/datasets/_processing_scripts/wu2020_3k.py
scirpy/get/__init__.py
scirpy/io/__init__.py
scirpy/io/_convert_anndata.py
scirpy/io/_datastructures.py
scirpy/io/_io.py
scirpy/io/_legacy.py
scirpy/io/_util.py
scirpy/io/_tracerlib/__init__.py
scirpy/io/_tracerlib/core.py
scirpy/ir_dist/__init__.py
scirpy/ir_dist/_clonotype_neighbors.py
scirpy/ir_dist/_util.py
scirpy/ir_dist/metrics.py
scirpy/pl/__init__.py
scirpy/pl/_clonal_expansion.py
scirpy/pl/_clonotype_imbalance.py
scirpy/pl/_clonotype_modularity.py
scirpy/pl/_clonotypes.py
scirpy/pl/_diversity.py
scirpy/pl/_group_abundance.py
scirpy/pl/_logoplots.py
scirpy/pl/_repertoire_overlap.py
scirpy/pl/_spectratype.py
scirpy/pl/_vdj_usage.py
scirpy/pl/base.py
scirpy/pl/styling.py
scirpy/pp/__init__.py
scirpy/pp/_index_chains.py
scirpy/pp/_merge_adata.py
scirpy/tests/__init__.py
scirpy/tests/conftest.py
scirpy/tests/test_clonotypes.py
scirpy/tests/test_datasets.py
scirpy/tests/test_get.py
scirpy/tests/test_io.py
scirpy/tests/test_ir_dist.py
scirpy/tests/test_ir_dist_metrics.py
scirpy/tests/test_ir_dist_util.py
scirpy/tests/test_ir_query.py
scirpy/tests/test_plotting.py
scirpy/tests/test_plotting_base.py
scirpy/tests/test_preprocessing.py
scirpy/tests/test_tools.py
scirpy/tests/test_util.py
scirpy/tests/test_workflow.py
scirpy/tests/util.py
scirpy/tests/data/wu2020_200.h5mu
scirpy/tests/data/wu2020_200_v0_11.h5ad
scirpy/tests/data/wu2020_200_v0_6.h5ad
scirpy/tests/data/10x/10k_BMMNC_5pv2_nextgem_Multiplex_vdj_t_all_contig_annotations_small.csv
scirpy/tests/data/10x/10k_BMMNC_5pv2_nextgem_Multiplex_vdj_t_all_contig_annotations_small.json
scirpy/tests/data/10x/all_contig_annotations.json
scirpy-0.22.5.dist-info/METADATA
scirpy-0.22.5.dist-info/WHEEL
scirpy-0.22.5.dist-info/licenses/LICENSE
scirpy-0.22.5.dist-info/RECORD
