Metadata-Version: 2.4
Name: scirpy
Version: 0.22.5
Summary: Python library for single-cell adaptive immune receptor repertoire (AIRR) analysis
Project-URL: Documentation, https://scirpy.readthedocs.io/
Project-URL: Home-page, https://github.com/scverse/scirpy
Project-URL: Source, https://github.com/scverse/scirpy
Author: Gregor Sturm, Tamas Szabo
Maintainer-email: Gregor Sturm <mail@gregor-sturm.de>
License: BSD 3-Clause License
License-File: LICENSE
Classifier: Programming Language :: Python :: 3 :: Only
Classifier: Programming Language :: Python :: 3.11
Classifier: Programming Language :: Python :: 3.12
Classifier: Programming Language :: Python :: 3.13
Classifier: Programming Language :: Python :: 3.14
Requires-Python: >=3.11
Requires-Dist: adjusttext>=0.7
Requires-Dist: airr>=1.4.1
Requires-Dist: anndata>=0.9
Requires-Dist: awkward>=2.1
Requires-Dist: igraph!=0.10,!=0.10.1
Requires-Dist: joblib>=1.3.1
Requires-Dist: logomaker!=0.8.5
Requires-Dist: mudata>=0.2.3
Requires-Dist: networkx>=2.5
Requires-Dist: numba>=0.60
Requires-Dist: numpy>=1.17
Requires-Dist: pandas!=2.1.2,>=1.5
Requires-Dist: pooch>=1.7
Requires-Dist: pycairo>=1.20; sys_platform == 'win32'
Requires-Dist: python-levenshtein
Requires-Dist: scanpy>=1.9.3
Requires-Dist: scikit-learn
Requires-Dist: scipy
Requires-Dist: squarify
Requires-Dist: tqdm>=4.63
Provides-Extra: cupy
Requires-Dist: cupy-cuda12x; extra == 'cupy'
Provides-Extra: dandelion
Requires-Dist: sc-dandelion>=0.3.5; extra == 'dandelion'
Provides-Extra: diversity
Requires-Dist: scikit-bio>=0.5.7; extra == 'diversity'
Provides-Extra: parasail
Requires-Dist: parasail!=1.2.1; extra == 'parasail'
Provides-Extra: rpack
Requires-Dist: rectangle-packer; extra == 'rpack'
